cvmcgmlst/__init__.py
cvmcgmlst/cgmlst_core.py
cvmcgmlst/cvmcgmlst.py
cvmcgmlst/db/demo.fsa
cvmcgmlst-0.2.6.dist-info/METADATA
cvmcgmlst-0.2.6.dist-info/WHEEL
cvmcgmlst-0.2.6.dist-info/entry_points.txt
cvmcgmlst-0.2.6.dist-info/top_level.txt
cvmcgmlst-0.2.6.dist-info/RECORD
