Metadata-Version: 2.1
Name: cvmcgmlst
Version: 0.2.6
Summary: cgMLST analysis tool
Home-page: https://github.com/hbucqp/cvmcgmlst
Author: Qingpo Cui
Author-email: cqp@cau.edu.cn
License: MIT Licence
Keywords: wgs,cgmlst
Platform: any
Classifier: Development Status :: 4 - Beta
Classifier: Intended Audience :: Developers
Classifier: Topic :: Software Development :: Build Tools
Classifier: License :: OSI Approved :: MIT License
Classifier: Programming Language :: Python :: 3
Classifier: Programming Language :: Python :: 3.8
Classifier: Programming Language :: Python :: 3.9
Classifier: Programming Language :: Python :: 3.10
Classifier: Programming Language :: Python :: 3.11
Requires-Dist: Bio
Requires-Dist: pandas
Requires-Dist: setuptools
Requires-Dist: cvmcore (>=0.2.2)
Requires-Dist: cvmblaster (>=0.4.9)
Requires-Dist: tabulate
